{"trial_id": "02", "hyperparameters": {"space": [{"class_name": "Int", "config": {"name": "units", "default": 50, "conditions": [], "min_value": 32, "max_value": 128, "step": 32, "sampling": "linear"}}, {"class_name": "Float", "config": {"name": "dropout_rate", "default": 0.2, "conditions": [], "min_value": 0.0, "max_value": 0.5, "step": 0.1, "sampling": "linear"}}], "values": {"units": 96, "dropout_rate": 0.1}}, "metrics": {"metrics": {"loss": {"direction": "min", "observations": [{"value": [0.0009084256598725915], "step": 2}]}, "mae": {"direction": "min", "observations": [{"value": [0.41317930817604065], "step": 2}]}, "val_loss": {"direction": "min", "observations": [{"value": [0.00043279308010824025], "step": 2}]}, "val_mae": {"direction": "min", "observations": [{"value": [0.5073338150978088], "step": 2}]}}}, "score": 0.00043279308010824025, "best_step": 2, "status": "COMPLETED", "message": null}